threedi_modelchecker/__init__.py
threedi_modelchecker/config.py
threedi_modelchecker/exporters.py
threedi_modelchecker/model_checks.py
threedi_modelchecker/scripts.py
threedi_modelchecker/checks/__init__.py
threedi_modelchecker/checks/base.py
threedi_modelchecker/checks/cross_section_definitions.py
threedi_modelchecker/checks/factories.py
threedi_modelchecker/checks/location.py
threedi_modelchecker/checks/other.py
threedi_modelchecker/checks/raster.py
threedi_modelchecker/checks/timeseries.py
threedi_modelchecker/interfaces/__init__.py
threedi_modelchecker/interfaces/raster_interface.py
threedi_modelchecker/interfaces/raster_interface_gdal.py
threedi_modelchecker/interfaces/raster_interface_rasterio.py
threedi_modelchecker/tests/__init__.py
threedi_modelchecker/tests/conftest.py
threedi_modelchecker/tests/factories.py
threedi_modelchecker/tests/test_checks_base.py
threedi_modelchecker/tests/test_checks_cross_section_definitions.py
threedi_modelchecker/tests/test_checks_factories.py
threedi_modelchecker/tests/test_checks_location.py
threedi_modelchecker/tests/test_checks_other.py
threedi_modelchecker/tests/test_checks_raster.py
threedi_modelchecker/tests/test_checks_timeseries.py
threedi_modelchecker/tests/test_error_messages.py
threedi_modelchecker/tests/test_exporters.py
threedi_modelchecker/tests/test_model_checks.py
threedi_modelchecker/tests/data/__init__.py
threedi_modelchecker/tests/data/empty.gpkg
threedi_modelchecker/tests/data/empty.sqlite
threedi_modelchecker-2.18.15.dist-info/licenses/LICENSE
threedi_modelchecker-2.18.15.dist-info/METADATA
threedi_modelchecker-2.18.15.dist-info/WHEEL
threedi_modelchecker-2.18.15.dist-info/entry_points.txt
threedi_modelchecker-2.18.15.dist-info/top_level.txt
threedi_modelchecker-2.18.15.dist-info/RECORD
