Metadata-Version: 2.4
Name: threedi-modelchecker
Version: 2.18.15
Summary: Checks validity of a 3Di schematisation
Author-email: Nelen & Schuurmans <info@nelen-schuurmans.nl>
License: MIT
Project-URL: Repository, https://github.com/nens/threedi-modelchecker
Classifier: Development Status :: 4 - Beta
Classifier: Intended Audience :: Developers
Classifier: Programming Language :: Python
Classifier: Programming Language :: Python :: 3
Requires-Python: >=3.9
License-File: LICENSE
Requires-Dist: Click
Requires-Dist: GeoAlchemy2!=0.11.*,>=0.9
Requires-Dist: SQLAlchemy>=1.4
Requires-Dist: pyproj
Requires-Dist: threedi-schema==0.300.*,>=0.300.23
Provides-Extra: rasterio
Requires-Dist: rasterio>=1.3.10; extra == "rasterio"
Provides-Extra: test
Requires-Dist: factory_boy; extra == "test"
Requires-Dist: pytest; extra == "test"
Requires-Dist: pytest-asyncio; extra == "test"
Requires-Dist: pytest-cov; extra == "test"
Dynamic: license-file
